phicache/__init__.py
phicache/cache.py
phicache/cache_item.py
phicache/strategy.py
phicache-0.1.2.dist-info/LICENSE
phicache-0.1.2.dist-info/METADATA
phicache-0.1.2.dist-info/WHEEL
phicache-0.1.2.dist-info/top_level.txt
phicache-0.1.2.dist-info/RECORD
